{"logs":[{"timestamp":1666362308059,"message":"system","level":0},{"timestamp":1666362308429,"message":"system","level":1},{"timestamp":1666362308762,"message":"system","level":2},{"timestamp":1666362308997,"message":"system","level":3},{"timestamp":1666362309146,"message":"system","level":4},{"timestamp":1666362793436,"message":"system","level":0},{"timestamp":1666362793579,"message":"system","level":1},{"timestamp":1666362793725,"message":"system","level":2},{"timestamp":1666362793866,"message":"system","level":3},{"timestamp":1666362793918,"message":"system","level":4},{"0":"b","1":"a","2":"f","3":"d","4":"d","5":"d","6":"d","7":"d","8":"d","9":"d","10":"d","11":"d","12":"d","13":"d","14":"d","15":"d","16":"d","17":"d","18":"d","19":"d","20":"d","21":"d","22":"d","23":"d","24":"d","25":"d","26":"d","27":"d","28":"d","29":"d","30":"d","31":"d","32":"d","33":"d","34":"d","35":"d","36":"d","37":"d","38":"d","39":"d","40":"d","41":"d","42":"d","43":"d","44":"d","45":"d","46":"d","47":"d","48":"d","49":"d","50":"d","51":"d","52":"d","53":"d","54":"d","55":"d","56":"d","57":"d","58":"d","59":"d","60":"d","timestamp":1666362905582},{"timestamp":1666363015568,"json":"bafdddddddddddddddddddddddddddddddddddddddddddddddddddddddddd"}]}